manim_stock/__init__.py
manim_stock/util/__init__.py
manim_stock/util/axes.py
manim_stock/util/barchart.py
manim_stock/util/const.py
manim_stock/util/dot.py
manim_stock/util/finance.py
manim_stock/util/graph.py
manim_stock/util/tex.py
manim_stock/util/title.py
manim_stock/visualization/__init__.py
manim_stock/visualization/barplot.py
manim_stock/visualization/growing_barplot.py
manim_stock/visualization/growing_lineplot.py
manim_stock/visualization/lineplot.py
manim_stock/visualization/plot.py
manim_stock_visualization-0.0.2.dist-info/METADATA
manim_stock_visualization-0.0.2.dist-info/WHEEL
manim_stock_visualization-0.0.2.dist-info/entry_points.txt
manim_stock_visualization-0.0.2.dist-info/licenses/LICENSE
manim_stock_visualization-0.0.2.dist-info/RECORD
