Metadata-Version: 2.1
Name: manim-stock-visualization
Version: 0.0.2
Summary: Visualization of stock prices using manimCE.
Author: Dennis Jabs
License: MIT License
Project-URL: Homepage, https://github.com/nobodyPerfecZ/manim-stock-visualization
Project-URL: Issues, https://github.com/nobodyPerfecZ/manim-stock-visualization/issues
Requires-Python: >=3.10
Requires-Dist: manim>=0.19.0
Requires-Dist: yfinance>=0.2.52
Requires-Dist: numpy>=2.2.2
Requires-Dist: pandas>=2.2.3
